Metadata-Version: 2.1
Name: filoc
Version: 0.0.24
Summary: eases the saving and reading of files within a structured folder tree
Home-page: https://github.com/jeromerg/filoc
Author: jeromerg
Author-email: jeromerg@gmx.net
Classifier: Programming Language :: Python :: 3
Classifier: License :: OSI Approved :: MIT License
Classifier: Operating System :: OS Independent
Requires-Python: >=3.6
License-File: LICENSE
Requires-Dist: fsspec
Requires-Dist: frozendict
Requires-Dist: pandas
Requires-Dist: pyyaml
